PDcompressor/__init__.py
PDcompressor/_pd_compressor.py
PDcompressor/pd_compressor.py
PDcompressor-0.1.1.dist-info/METADATA
PDcompressor-0.1.1.dist-info/WHEEL
PDcompressor-0.1.1.dist-info/top_level.txt
PDcompressor-0.1.1.dist-info/RECORD
