Metadata-Version: 2.1
Name: PDcompressor
Version: 0.1.1
Summary: Package for compress storage dataframe
Home-page: https://github.com/Ho-Jun-Moon/pandas_storage_compressor
Author: papamoon0113
Author-email: papamoon0113@pusan.ac.kr
License: UNKNOWN
Platform: UNKNOWN
Classifier: Programming Language :: Python :: 3
Classifier: License :: OSI Approved :: MIT License
Classifier: Operating System :: OS Independent
Requires-Python: >=3.6
Requires-Dist: pandas
Requires-Dist: numpy
